CHANGES.txt
CONTRIBUTORS.txt
LICENSE.txt
MANIFEST.in
README.txt
setup.py
examples/intro_to_prysenter.py
examples/unit_testing_and_me.py
prysenter/__init__.py
prysenter/colors.py
prysenter/formatters.py
prysenter/pechakucha.py
prysenter/prysenter.py
prysenter/shtf.py
prysenter.egg-info/PKG-INFO
prysenter.egg-info/SOURCES.txt
prysenter.egg-info/dependency_links.txt
prysenter.egg-info/requires.txt
prysenter.egg-info/top_level.txt